polars_maxminddb-0.2.3.dist-info/METADATA
polars_maxminddb-0.2.3.dist-info/WHEEL
polars_maxminddb/_internal.pyi
polars_maxminddb/typing.py
polars_maxminddb/__init__.py
polars_maxminddb/_internal.abi3.so
polars_maxminddb-0.2.3.dist-info/RECORD
