Metadata-Version: 2.4
Name: polars-maxminddb
Version: 0.2.3
Classifier: Programming Language :: Rust
Classifier: Programming Language :: Python :: Implementation :: CPython
Classifier: Programming Language :: Python :: Implementation :: PyPy
Requires-Dist: maturin >=1.7.4
Requires-Dist: polars >=1.8.2
Requires-Dist: pytest >=8.3.3
Requires-Python: >=3.8
